{
  "type": "File",
  "start": 0,
  "end": 1368,
  "loc": {
    "start": {
      "line": 1,
      "column": 0
    },
    "end": {
      "line": 44,
      "column": 0
    }
  },
  "program": {
    "type": "Program",
    "start": 0,
    "end": 1368,
    "loc": {
      "start": {
        "line": 1,
        "column": 0
      },
      "end": {
        "line": 44,
        "column": 0
      }
    },
    "sourceType": "module",
    "body": [
      {
        "type": "ImportDeclaration",
        "start": 70,
        "end": 106,
        "loc": {
          "start": {
            "line": 3,
            "column": 0
          },
          "end": {
            "line": 3,
            "column": 36
          }
        },
        "specifiers": [
          {
            "type": "ImportNamespaceSpecifier",
            "start": 77,
            "end": 89,
            "loc": {
              "start": {
                "line": 3,
                "column": 7
              },
              "end": {
                "line": 3,
                "column": 19
              }
            },
            "local": {
              "type": "Identifier",
              "start": 82,
              "end": 89,
              "loc": {
                "start": {
                  "line": 3,
                  "column": 12
                },
                "end": {
                  "line": 3,
                  "column": 19
                },
                "identifierName": "gateway"
              },
              "name": "gateway",
              "leadingComments": null
            },
            "leadingComments": null
          }
        ],
        "source": {
          "type": "StringLiteral",
          "start": 95,
          "end": 106,
          "loc": {
            "start": {
              "line": 3,
              "column": 25
            },
            "end": {
              "line": 3,
              "column": 36
            }
          },
          "extra": {
            "rawValue": "./gateway",
            "raw": "'./gateway'"
          },
          "value": "./gateway",
          "leadingComments": null,
          "trailingComments": null
        },
        "leadingComments": [
          {
            "type": "CommentBlock",
            "value": "* @module Insurance ",
            "start": 0,
            "end": 24,
            "loc": {
              "start": {
                "line": 1,
                "column": 0
              },
              "end": {
                "line": 1,
                "column": 24
              }
            }
          },
          {
            "type": "CommentLine",
            "value": " Auto-generated, edits will be overwritten",
            "start": 25,
            "end": 69,
            "loc": {
              "start": {
                "line": 2,
                "column": 0
              },
              "end": {
                "line": 2,
                "column": 44
              }
            }
          }
        ],
        "trailingComments": [
          {
            "type": "CommentBlock",
            "value": "*\n * Return available insurance levels for all ship types\n * \n * ---\n * Alternate route: `/dev/insurance/prices/`\n * \n * Alternate route: `/legacy/insurance/prices/`\n * \n * Alternate route: `/v1/insurance/prices/`\n * \n * ---\n * This route is cached for up to 3600 seconds\n * \n * @param {object} options Optional options\n * @param {string} [options.AcceptLanguage] Language to use in the response\n * @param {string} [options.datasource] The server name you would like data from\n * @param {string} [options.IfNoneMatch] ETag from a previous request. A 304 will be returned if this matches the current ETag\n * @param {string} [options.language] Language to use in the response, takes precedence over Accept-Language\n * @return {Promise<object>} A list of insurance levels for all ship types\n ",
            "start": 108,
            "end": 901,
            "loc": {
              "start": {
                "line": 5,
                "column": 0
              },
              "end": {
                "line": 24,
                "column": 3
              }
            }
          }
        ]
      },
      {
        "type": "ExportNamedDeclaration",
        "start": 902,
        "end": 1278,
        "loc": {
          "start": {
            "line": 25,
            "column": 0
          },
          "end": {
            "line": 38,
            "column": 1
          }
        },
        "specifiers": [],
        "source": null,
        "declaration": {
          "type": "FunctionDeclaration",
          "start": 909,
          "end": 1278,
          "loc": {
            "start": {
              "line": 25,
              "column": 7
            },
            "end": {
              "line": 38,
              "column": 1
            }
          },
          "id": {
            "type": "Identifier",
            "start": 918,
            "end": 938,
            "loc": {
              "start": {
                "line": 25,
                "column": 16
              },
              "end": {
                "line": 25,
                "column": 36
              },
              "identifierName": "get_insurance_prices"
            },
            "name": "get_insurance_prices",
            "leadingComments": null
          },
          "generator": false,
          "expression": false,
          "async": false,
          "params": [
            {
              "type": "Identifier",
              "start": 939,
              "end": 946,
              "loc": {
                "start": {
                  "line": 25,
                  "column": 37
                },
                "end": {
                  "line": 25,
                  "column": 44
                },
                "identifierName": "options"
              },
              "name": "options"
            }
          ],
          "body": {
            "type": "BlockStatement",
            "start": 948,
            "end": 1278,
            "loc": {
              "start": {
                "line": 25,
                "column": 46
              },
              "end": {
                "line": 38,
                "column": 1
              }
            },
            "body": [
              {
                "type": "IfStatement",
                "start": 952,
                "end": 978,
                "loc": {
                  "start": {
                    "line": 26,
                    "column": 2
                  },
                  "end": {
                    "line": 26,
                    "column": 28
                  }
                },
                "test": {
                  "type": "UnaryExpression",
                  "start": 956,
                  "end": 964,
                  "loc": {
                    "start": {
                      "line": 26,
                      "column": 6
                    },
                    "end": {
                      "line": 26,
                      "column": 14
                    }
                  },
                  "operator": "!",
                  "prefix": true,
                  "argument": {
                    "type": "Identifier",
                    "start": 957,
                    "end": 964,
                    "loc": {
                      "start": {
                        "line": 26,
                        "column": 7
                      },
                      "end": {
                        "line": 26,
                        "column": 14
                      },
                      "identifierName": "options"
                    },
                    "name": "options"
                  },
                  "extra": {
                    "parenthesizedArgument": false
                  }
                },
                "consequent": {
                  "type": "ExpressionStatement",
                  "start": 966,
                  "end": 978,
                  "loc": {
                    "start": {
                      "line": 26,
                      "column": 16
                    },
                    "end": {
                      "line": 26,
                      "column": 28
                    }
                  },
                  "expression": {
                    "type": "AssignmentExpression",
                    "start": 966,
                    "end": 978,
                    "loc": {
                      "start": {
                        "line": 26,
                        "column": 16
                      },
                      "end": {
                        "line": 26,
                        "column": 28
                      }
                    },
                    "operator": "=",
                    "left": {
                      "type": "Identifier",
                      "start": 966,
                      "end": 973,
                      "loc": {
                        "start": {
                          "line": 26,
                          "column": 16
                        },
                        "end": {
                          "line": 26,
                          "column": 23
                        },
                        "identifierName": "options"
                      },
                      "name": "options"
                    },
                    "right": {
                      "type": "ObjectExpression",
                      "start": 976,
                      "end": 978,
                      "loc": {
                        "start": {
                          "line": 26,
                          "column": 26
                        },
                        "end": {
                          "line": 26,
                          "column": 28
                        }
                      },
                      "properties": []
                    }
                  }
                },
                "alternate": null
              },
              {
                "type": "VariableDeclaration",
                "start": 981,
                "end": 1208,
                "loc": {
                  "start": {
                    "line": 27,
                    "column": 2
                  },
                  "end": {
                    "line": 36,
                    "column": 3
                  }
                },
                "declarations": [
                  {
                    "type": "VariableDeclarator",
                    "start": 987,
                    "end": 1208,
                    "loc": {
                      "start": {
                        "line": 27,
                        "column": 8
                      },
                      "end": {
                        "line": 36,
                        "column": 3
                      }
                    },
                    "id": {
                      "type": "Identifier",
                      "start": 987,
                      "end": 997,
                      "loc": {
                        "start": {
                          "line": 27,
                          "column": 8
                        },
                        "end": {
                          "line": 27,
                          "column": 18
                        },
                        "identifierName": "parameters"
                      },
                      "name": "parameters"
                    },
                    "init": {
                      "type": "ObjectExpression",
                      "start": 1000,
                      "end": 1208,
                      "loc": {
                        "start": {
                          "line": 27,
                          "column": 21
                        },
                        "end": {
                          "line": 36,
                          "column": 3
                        }
                      },
                      "properties": [
                        {
                          "type": "ObjectProperty",
                          "start": 1006,
                          "end": 1113,
                          "loc": {
                            "start": {
                              "line": 28,
                              "column": 4
                            },
                            "end": {
                              "line": 31,
                              "column": 5
                            }
                          },
                          "method": false,
                          "shorthand": false,
                          "computed": false,
                          "key": {
                            "type": "Identifier",
                            "start": 1006,
                            "end": 1012,
                            "loc": {
                              "start": {
                                "line": 28,
                                "column": 4
                              },
                              "end": {
                                "line": 28,
                                "column": 10
                              },
                              "identifierName": "header"
                            },
                            "name": "header"
                          },
                          "value": {
                            "type": "ObjectExpression",
                            "start": 1014,
                            "end": 1113,
                            "loc": {
                              "start": {
                                "line": 28,
                                "column": 12
                              },
                              "end": {
                                "line": 31,
                                "column": 5
                              }
                            },
                            "properties": [
                              {
                                "type": "ObjectProperty",
                                "start": 1022,
                                "end": 1063,
                                "loc": {
                                  "start": {
                                    "line": 29,
                                    "column": 6
                                  },
                                  "end": {
                                    "line": 29,
                                    "column": 47
                                  }
                                },
                                "method": false,
                                "shorthand": false,
                                "computed": false,
                                "key": {
                                  "type": "StringLiteral",
                                  "start": 1022,
                                  "end": 1039,
                                  "loc": {
                                    "start": {
                                      "line": 29,
                                      "column": 6
                                    },
                                    "end": {
                                      "line": 29,
                                      "column": 23
                                    }
                                  },
                                  "extra": {
                                    "rawValue": "Accept-Language",
                                    "raw": "'Accept-Language'"
                                  },
                                  "value": "Accept-Language"
                                },
                                "value": {
                                  "type": "MemberExpression",
                                  "start": 1041,
                                  "end": 1063,
                                  "loc": {
                                    "start": {
                                      "line": 29,
                                      "column": 25
                                    },
                                    "end": {
                                      "line": 29,
                                      "column": 47
                                    }
                                  },
                                  "object": {
                                    "type": "Identifier",
                                    "start": 1041,
                                    "end": 1048,
                                    "loc": {
                                      "start": {
                                        "line": 29,
                                        "column": 25
                                      },
                                      "end": {
                                        "line": 29,
                                        "column": 32
                                      },
                                      "identifierName": "options"
                                    },
                                    "name": "options"
                                  },
                                  "property": {
                                    "type": "Identifier",
                                    "start": 1049,
                                    "end": 1063,
                                    "loc": {
                                      "start": {
                                        "line": 29,
                                        "column": 33
                                      },
                                      "end": {
                                        "line": 29,
                                        "column": 47
                                      },
                                      "identifierName": "AcceptLanguage"
                                    },
                                    "name": "AcceptLanguage"
                                  },
                                  "computed": false
                                }
                              },
                              {
                                "type": "ObjectProperty",
                                "start": 1071,
                                "end": 1107,
                                "loc": {
                                  "start": {
                                    "line": 30,
                                    "column": 6
                                  },
                                  "end": {
                                    "line": 30,
                                    "column": 42
                                  }
                                },
                                "method": false,
                                "shorthand": false,
                                "computed": false,
                                "key": {
                                  "type": "StringLiteral",
                                  "start": 1071,
                                  "end": 1086,
                                  "loc": {
                                    "start": {
                                      "line": 30,
                                      "column": 6
                                    },
                                    "end": {
                                      "line": 30,
                                      "column": 21
                                    }
                                  },
                                  "extra": {
                                    "rawValue": "If-None-Match",
                                    "raw": "'If-None-Match'"
                                  },
                                  "value": "If-None-Match"
                                },
                                "value": {
                                  "type": "MemberExpression",
                                  "start": 1088,
                                  "end": 1107,
                                  "loc": {
                                    "start": {
                                      "line": 30,
                                      "column": 23
                                    },
                                    "end": {
                                      "line": 30,
                                      "column": 42
                                    }
                                  },
                                  "object": {
                                    "type": "Identifier",
                                    "start": 1088,
                                    "end": 1095,
                                    "loc": {
                                      "start": {
                                        "line": 30,
                                        "column": 23
                                      },
                                      "end": {
                                        "line": 30,
                                        "column": 30
                                      },
                                      "identifierName": "options"
                                    },
                                    "name": "options"
                                  },
                                  "property": {
                                    "type": "Identifier",
                                    "start": 1096,
                                    "end": 1107,
                                    "loc": {
                                      "start": {
                                        "line": 30,
                                        "column": 31
                                      },
                                      "end": {
                                        "line": 30,
                                        "column": 42
                                      },
                                      "identifierName": "IfNoneMatch"
                                    },
                                    "name": "IfNoneMatch"
                                  },
                                  "computed": false
                                }
                              }
                            ]
                          }
                        },
                        {
                          "type": "ObjectProperty",
                          "start": 1119,
                          "end": 1204,
                          "loc": {
                            "start": {
                              "line": 32,
                              "column": 4
                            },
                            "end": {
                              "line": 35,
                              "column": 5
                            }
                          },
                          "method": false,
                          "shorthand": false,
                          "computed": false,
                          "key": {
                            "type": "Identifier",
                            "start": 1119,
                            "end": 1124,
                            "loc": {
                              "start": {
                                "line": 32,
                                "column": 4
                              },
                              "end": {
                                "line": 32,
                                "column": 9
                              },
                              "identifierName": "query"
                            },
                            "name": "query"
                          },
                          "value": {
                            "type": "ObjectExpression",
                            "start": 1126,
                            "end": 1204,
                            "loc": {
                              "start": {
                                "line": 32,
                                "column": 11
                              },
                              "end": {
                                "line": 35,
                                "column": 5
                              }
                            },
                            "properties": [
                              {
                                "type": "ObjectProperty",
                                "start": 1134,
                                "end": 1164,
                                "loc": {
                                  "start": {
                                    "line": 33,
                                    "column": 6
                                  },
                                  "end": {
                                    "line": 33,
                                    "column": 36
                                  }
                                },
                                "method": false,
                                "shorthand": false,
                                "computed": false,
                                "key": {
                                  "type": "Identifier",
                                  "start": 1134,
                                  "end": 1144,
                                  "loc": {
                                    "start": {
                                      "line": 33,
                                      "column": 6
                                    },
                                    "end": {
                                      "line": 33,
                                      "column": 16
                                    },
                                    "identifierName": "datasource"
                                  },
                                  "name": "datasource"
                                },
                                "value": {
                                  "type": "MemberExpression",
                                  "start": 1146,
                                  "end": 1164,
                                  "loc": {
                                    "start": {
                                      "line": 33,
                                      "column": 18
                                    },
                                    "end": {
                                      "line": 33,
                                      "column": 36
                                    }
                                  },
                                  "object": {
                                    "type": "Identifier",
                                    "start": 1146,
                                    "end": 1153,
                                    "loc": {
                                      "start": {
                                        "line": 33,
                                        "column": 18
                                      },
                                      "end": {
                                        "line": 33,
                                        "column": 25
                                      },
                                      "identifierName": "options"
                                    },
                                    "name": "options"
                                  },
                                  "property": {
                                    "type": "Identifier",
                                    "start": 1154,
                                    "end": 1164,
                                    "loc": {
                                      "start": {
                                        "line": 33,
                                        "column": 26
                                      },
                                      "end": {
                                        "line": 33,
                                        "column": 36
                                      },
                                      "identifierName": "datasource"
                                    },
                                    "name": "datasource"
                                  },
                                  "computed": false
                                }
                              },
                              {
                                "type": "ObjectProperty",
                                "start": 1172,
                                "end": 1198,
                                "loc": {
                                  "start": {
                                    "line": 34,
                                    "column": 6
                                  },
                                  "end": {
                                    "line": 34,
                                    "column": 32
                                  }
                                },
                                "method": false,
                                "shorthand": false,
                                "computed": false,
                                "key": {
                                  "type": "Identifier",
                                  "start": 1172,
                                  "end": 1180,
                                  "loc": {
                                    "start": {
                                      "line": 34,
                                      "column": 6
                                    },
                                    "end": {
                                      "line": 34,
                                      "column": 14
                                    },
                                    "identifierName": "language"
                                  },
                                  "name": "language"
                                },
                                "value": {
                                  "type": "MemberExpression",
                                  "start": 1182,
                                  "end": 1198,
                                  "loc": {
                                    "start": {
                                      "line": 34,
                                      "column": 16
                                    },
                                    "end": {
                                      "line": 34,
                                      "column": 32
                                    }
                                  },
                                  "object": {
                                    "type": "Identifier",
                                    "start": 1182,
                                    "end": 1189,
                                    "loc": {
                                      "start": {
                                        "line": 34,
                                        "column": 16
                                      },
                                      "end": {
                                        "line": 34,
                                        "column": 23
                                      },
                                      "identifierName": "options"
                                    },
                                    "name": "options"
                                  },
                                  "property": {
                                    "type": "Identifier",
                                    "start": 1190,
                                    "end": 1198,
                                    "loc": {
                                      "start": {
                                        "line": 34,
                                        "column": 24
                                      },
                                      "end": {
                                        "line": 34,
                                        "column": 32
                                      },
                                      "identifierName": "language"
                                    },
                                    "name": "language"
                                  },
                                  "computed": false
                                }
                              }
                            ]
                          }
                        }
                      ]
                    }
                  }
                ],
                "kind": "const"
              },
              {
                "type": "ReturnStatement",
                "start": 1211,
                "end": 1276,
                "loc": {
                  "start": {
                    "line": 37,
                    "column": 2
                  },
                  "end": {
                    "line": 37,
                    "column": 67
                  }
                },
                "argument": {
                  "type": "CallExpression",
                  "start": 1218,
                  "end": 1276,
                  "loc": {
                    "start": {
                      "line": 37,
                      "column": 9
                    },
                    "end": {
                      "line": 37,
                      "column": 67
                    }
                  },
                  "callee": {
                    "type": "MemberExpression",
                    "start": 1218,
                    "end": 1233,
                    "loc": {
                      "start": {
                        "line": 37,
                        "column": 9
                      },
                      "end": {
                        "line": 37,
                        "column": 24
                      }
                    },
                    "object": {
                      "type": "Identifier",
                      "start": 1218,
                      "end": 1225,
                      "loc": {
                        "start": {
                          "line": 37,
                          "column": 9
                        },
                        "end": {
                          "line": 37,
                          "column": 16
                        },
                        "identifierName": "gateway"
                      },
                      "name": "gateway"
                    },
                    "property": {
                      "type": "Identifier",
                      "start": 1226,
                      "end": 1233,
                      "loc": {
                        "start": {
                          "line": 37,
                          "column": 17
                        },
                        "end": {
                          "line": 37,
                          "column": 24
                        },
                        "identifierName": "request"
                      },
                      "name": "request"
                    },
                    "computed": false
                  },
                  "arguments": [
                    {
                      "type": "Identifier",
                      "start": 1234,
                      "end": 1263,
                      "loc": {
                        "start": {
                          "line": 37,
                          "column": 25
                        },
                        "end": {
                          "line": 37,
                          "column": 54
                        },
                        "identifierName": "get_insurance_pricesOperation"
                      },
                      "name": "get_insurance_pricesOperation"
                    },
                    {
                      "type": "Identifier",
                      "start": 1265,
                      "end": 1275,
                      "loc": {
                        "start": {
                          "line": 37,
                          "column": 56
                        },
                        "end": {
                          "line": 37,
                          "column": 66
                        },
                        "identifierName": "parameters"
                      },
                      "name": "parameters"
                    }
                  ]
                }
              }
            ],
            "directives": []
          },
          "leadingComments": [
            {
              "type": "CommentBlock",
              "value": "*\n * Return available insurance levels for all ship types\n * \n * ---\n * Alternate route: `/dev/insurance/prices/`\n * \n * Alternate route: `/legacy/insurance/prices/`\n * \n * Alternate route: `/v1/insurance/prices/`\n * \n * ---\n * This route is cached for up to 3600 seconds\n * \n * @param {object} options Optional options\n * @param {string} [options.AcceptLanguage] Language to use in the response\n * @param {string} [options.datasource] The server name you would like data from\n * @param {string} [options.IfNoneMatch] ETag from a previous request. A 304 will be returned if this matches the current ETag\n * @param {string} [options.language] Language to use in the response, takes precedence over Accept-Language\n * @return {Promise<object>} A list of insurance levels for all ship types\n ",
              "start": 108,
              "end": 901,
              "loc": {
                "start": {
                  "line": 5,
                  "column": 0
                },
                "end": {
                  "line": 24,
                  "column": 3
                }
              }
            }
          ],
          "trailingComments": []
        },
        "leadingComments": [
          {
            "type": "CommentBlock",
            "value": "*\n * Return available insurance levels for all ship types\n * \n * ---\n * Alternate route: `/dev/insurance/prices/`\n * \n * Alternate route: `/legacy/insurance/prices/`\n * \n * Alternate route: `/v1/insurance/prices/`\n * \n * ---\n * This route is cached for up to 3600 seconds\n * \n * @param {object} options Optional options\n * @param {string} [options.AcceptLanguage] Language to use in the response\n * @param {string} [options.datasource] The server name you would like data from\n * @param {string} [options.IfNoneMatch] ETag from a previous request. A 304 will be returned if this matches the current ETag\n * @param {string} [options.language] Language to use in the response, takes precedence over Accept-Language\n * @return {Promise<object>} A list of insurance levels for all ship types\n ",
            "start": 108,
            "end": 901,
            "loc": {
              "start": {
                "line": 5,
                "column": 0
              },
              "end": {
                "line": 24,
                "column": 3
              }
            }
          }
        ]
      },
      {
        "type": "VariableDeclaration",
        "start": 1280,
        "end": 1367,
        "loc": {
          "start": {
            "line": 40,
            "column": 0
          },
          "end": {
            "line": 43,
            "column": 1
          }
        },
        "declarations": [
          {
            "type": "VariableDeclarator",
            "start": 1286,
            "end": 1367,
            "loc": {
              "start": {
                "line": 40,
                "column": 6
              },
              "end": {
                "line": 43,
                "column": 1
              }
            },
            "id": {
              "type": "Identifier",
              "start": 1286,
              "end": 1315,
              "loc": {
                "start": {
                  "line": 40,
                  "column": 6
                },
                "end": {
                  "line": 40,
                  "column": 35
                },
                "identifierName": "get_insurance_pricesOperation"
              },
              "name": "get_insurance_pricesOperation"
            },
            "init": {
              "type": "ObjectExpression",
              "start": 1318,
              "end": 1367,
              "loc": {
                "start": {
                  "line": 40,
                  "column": 38
                },
                "end": {
                  "line": 43,
                  "column": 1
                }
              },
              "properties": [
                {
                  "type": "ObjectProperty",
                  "start": 1322,
                  "end": 1348,
                  "loc": {
                    "start": {
                      "line": 41,
                      "column": 2
                    },
                    "end": {
                      "line": 41,
                      "column": 28
                    }
                  },
                  "method": false,
                  "shorthand": false,
                  "computed": false,
                  "key": {
                    "type": "Identifier",
                    "start": 1322,
                    "end": 1326,
                    "loc": {
                      "start": {
                        "line": 41,
                        "column": 2
                      },
                      "end": {
                        "line": 41,
                        "column": 6
                      },
                      "identifierName": "path"
                    },
                    "name": "path"
                  },
                  "value": {
                    "type": "StringLiteral",
                    "start": 1328,
                    "end": 1348,
                    "loc": {
                      "start": {
                        "line": 41,
                        "column": 8
                      },
                      "end": {
                        "line": 41,
                        "column": 28
                      }
                    },
                    "extra": {
                      "rawValue": "/insurance/prices/",
                      "raw": "'/insurance/prices/'"
                    },
                    "value": "/insurance/prices/"
                  }
                },
                {
                  "type": "ObjectProperty",
                  "start": 1352,
                  "end": 1365,
                  "loc": {
                    "start": {
                      "line": 42,
                      "column": 2
                    },
                    "end": {
                      "line": 42,
                      "column": 15
                    }
                  },
                  "method": false,
                  "shorthand": false,
                  "computed": false,
                  "key": {
                    "type": "Identifier",
                    "start": 1352,
                    "end": 1358,
                    "loc": {
                      "start": {
                        "line": 42,
                        "column": 2
                      },
                      "end": {
                        "line": 42,
                        "column": 8
                      },
                      "identifierName": "method"
                    },
                    "name": "method"
                  },
                  "value": {
                    "type": "StringLiteral",
                    "start": 1360,
                    "end": 1365,
                    "loc": {
                      "start": {
                        "line": 42,
                        "column": 10
                      },
                      "end": {
                        "line": 42,
                        "column": 15
                      }
                    },
                    "extra": {
                      "rawValue": "get",
                      "raw": "'get'"
                    },
                    "value": "get"
                  }
                }
              ]
            }
          }
        ],
        "kind": "const"
      }
    ],
    "directives": []
  },
  "comments": [
    {
      "type": "CommentBlock",
      "value": "* @module Insurance ",
      "start": 0,
      "end": 24,
      "loc": {
        "start": {
          "line": 1,
          "column": 0
        },
        "end": {
          "line": 1,
          "column": 24
        }
      }
    },
    {
      "type": "CommentLine",
      "value": " Auto-generated, edits will be overwritten",
      "start": 25,
      "end": 69,
      "loc": {
        "start": {
          "line": 2,
          "column": 0
        },
        "end": {
          "line": 2,
          "column": 44
        }
      }
    },
    {
      "type": "CommentBlock",
      "value": "*\n * Return available insurance levels for all ship types\n * \n * ---\n * Alternate route: `/dev/insurance/prices/`\n * \n * Alternate route: `/legacy/insurance/prices/`\n * \n * Alternate route: `/v1/insurance/prices/`\n * \n * ---\n * This route is cached for up to 3600 seconds\n * \n * @param {object} options Optional options\n * @param {string} [options.AcceptLanguage] Language to use in the response\n * @param {string} [options.datasource] The server name you would like data from\n * @param {string} [options.IfNoneMatch] ETag from a previous request. A 304 will be returned if this matches the current ETag\n * @param {string} [options.language] Language to use in the response, takes precedence over Accept-Language\n * @return {Promise<object>} A list of insurance levels for all ship types\n ",
      "start": 108,
      "end": 901,
      "loc": {
        "start": {
          "line": 5,
          "column": 0
        },
        "end": {
          "line": 24,
          "column": 3
        }
      }
    }
  ],
  "tokens": [
    {
      "type": "CommentBlock",
      "value": "* @module Insurance ",
      "start": 0,
      "end": 24,
      "loc": {
        "start": {
          "line": 1,
          "column": 0
        },
        "end": {
          "line": 1,
          "column": 24
        }
      }
    },
    {
      "type": "CommentLine",
      "value": " Auto-generated, edits will be overwritten",
      "start": 25,
      "end": 69,
      "loc": {
        "start": {
          "line": 2,
          "column": 0
        },
        "end": {
          "line": 2,
          "column": 44
        }
      }
    },
    {
      "type": {
        "label": "import",
        "keyword": "import",
        "beforeExpr": false,
        "startsExpr": true,
        "rightAssociative": false,
        "isLoop": false,
        "isAssign": false,
        "prefix": false,
        "postfix": false,
        "binop": null,
        "updateContext": null
      },
      "value": "import",
      "start": 70,
      "end": 76,
      "loc": {
        "start": {
          "line": 3,
          "column": 0
        },
        "end": {
          "line": 3,
          "column": 6
        }
      }
    },
    {
      "type": {
        "label": "*",
        "beforeExpr": true,
        "startsExpr": false,
        "rightAssociative": false,
        "isLoop": false,
        "isAssign": false,
        "prefix": false,
        "postfix": false,
        "binop": 10,
        "updateContext": null
      },
      "value": "*",
      "start": 77,
      "end": 78,
      "loc": {
        "start": {
          "line": 3,
          "column": 7
        },
        "end": {
          "line": 3,
          "column": 8
        }
      }
    },
    {
      "type": {
        "label": "name",
        "beforeExpr": false,
        "startsExpr": true,
        "rightAssociative": false,
        "isLoop": false,
        "isAssign": false,
        "prefix": false,
        "postfix": false,
        "binop": null
      },
      "value": "as",
      "start": 79,
      "end": 81,
      "loc": {
        "start": {
          "line": 3,
          "column": 9
        },
        "end": {
          "line": 3,
          "column": 11
        }
      }
    },
    {
      "type": {
        "label": "name",
        "beforeExpr": false,
        "startsExpr": true,
        "rightAssociative": false,
        "isLoop": false,
        "isAssign": false,
        "prefix": false,
        "postfix": false,
        "binop": null
      },
      "value": "gateway",
      "start": 82,
      "end": 89,
      "loc": {
        "start": {
          "line": 3,
          "column": 12
        },
        "end": {
          "line": 3,
          "column": 19
        }
      }
    },
    {
      "type": {
        "label": "name",
        "beforeExpr": false,
        "startsExpr": true,
        "rightAssociative": false,
        "isLoop": false,
        "isAssign": false,
        "prefix": false,
        "postfix": false,
        "binop": null
      },
      "value": "from",
      "start": 90,
      "end": 94,
      "loc": {
        "start": {
          "line": 3,
          "column": 20
        },
        "end": {
          "line": 3,
          "column": 24
        }
      }
    },
    {
      "type": {
        "label": "string",
        "beforeExpr": false,
        "startsExpr": true,
        "rightAssociative": false,
        "isLoop": false,
        "isAssign": false,
        "prefix": false,
        "postfix": false,
        "binop": null,
        "updateContext": null
      },
      "value": "./gateway",
      "start": 95,
      "end": 106,
      "loc": {
        "start": {
          "line": 3,
          "column": 25
        },
        "end": {
          "line": 3,
          "column": 36
        }
      }
    },
    {
      "type": "CommentBlock",
      "value": "*\n * Return available insurance levels for all ship types\n * \n * ---\n * Alternate route: `/dev/insurance/prices/`\n * \n * Alternate route: `/legacy/insurance/prices/`\n * \n * Alternate route: `/v1/insurance/prices/`\n * \n * ---\n * This route is cached for up to 3600 seconds\n * \n * @param {object} options Optional options\n * @param {string} [options.AcceptLanguage] Language to use in the response\n * @param {string} [options.datasource] The server name you would like data from\n * @param {string} [options.IfNoneMatch] ETag from a previous request. A 304 will be returned if this matches the current ETag\n * @param {string} [options.language] Language to use in the response, takes precedence over Accept-Language\n * @return {Promise<object>} A list of insurance levels for all ship types\n ",
      "start": 108,
      "end": 901,
      "loc": {
        "start": {
          "line": 5,
          "column": 0
        },
        "end": {
          "line": 24,
          "column": 3
        }
      }
    },
    {
      "type": {
        "label": "export",
        "keyword": "export",
        "beforeExpr": false,
        "startsExpr": false,
        "rightAssociative": false,
        "isLoop": false,
        "isAssign": false,
        "prefix": false,
        "postfix": false,
        "binop": null,
        "updateContext": null
      },
      "value": "export",
      "start": 902,
      "end": 908,
      "loc": {
        "start": {
          "line": 25,
          "column": 0
        },
        "end": {
          "line": 25,
          "column": 6
        }
      }
    },
    {
      "type": {
        "label": "function",
        "keyword": "function",
        "beforeExpr": false,
        "startsExpr": true,
        "rightAssociative": false,
        "isLoop": false,
        "isAssign": false,
        "prefix": false,
        "postfix": false,
        "binop": null
      },
      "value": "function",
      "start": 909,
      "end": 917,
      "loc": {
        "start": {
          "line": 25,
          "column": 7
        },
        "end": {
          "line": 25,
          "column": 15
        }
      }
    },
    {
      "type": {
        "label": "name",
        "beforeExpr": false,
        "startsExpr": true,
        "rightAssociative": false,
        "isLoop": false,
        "isAssign": false,
        "prefix": false,
        "postfix": false,
        "binop": null
      },
      "value": "get_insurance_prices",
      "start": 918,
      "end": 938,
      "loc": {
        "start": {
          "line": 25,
          "column": 16
        },
        "end": {
          "line": 25,
          "column": 36
        }
      }
    },
    {
      "type": {
        "label": "(",
        "beforeExpr": true,
        "startsExpr": true,
        "rightAssociative": false,
        "isLoop": false,
        "isAssign": false,
        "prefix": false,
        "postfix": false,
        "binop": null
      },
      "start": 938,
      "end": 939,
      "loc": {
        "start": {
          "line": 25,
          "column": 36
        },
        "end": {
          "line": 25,
          "column": 37
        }
      }
    },
    {
      "type": {
        "label": "name",
        "beforeExpr": false,
        "startsExpr": true,
        "rightAssociative": false,
        "isLoop": false,
        "isAssign": false,
        "prefix": false,
        "postfix": false,
        "binop": null
      },
      "value": "options",
      "start": 939,
      "end": 946,
      "loc": {
        "start": {
          "line": 25,
          "column": 37
        },
        "end": {
          "line": 25,
          "column": 44
        }
      }
    },
    {
      "type": {
        "label": ")",
        "beforeExpr": false,
        "startsExpr": false,
        "rightAssociative": false,
        "isLoop": false,
        "isAssign": false,
        "prefix": false,
        "postfix": false,
        "binop": null
      },
      "start": 946,
      "end": 947,
      "loc": {
        "start": {
          "line": 25,
          "column": 44
        },
        "end": {
          "line": 25,
          "column": 45
        }
      }
    },
    {
      "type": {
        "label": "{",
        "beforeExpr": true,
        "startsExpr": true,
        "rightAssociative": false,
        "isLoop": false,
        "isAssign": false,
        "prefix": false,
        "postfix": false,
        "binop": null
      },
      "start": 948,
      "end": 949,
      "loc": {
        "start": {
          "line": 25,
          "column": 46
        },
        "end": {
          "line": 25,
          "column": 47
        }
      }
    },
    {
      "type": {
        "label": "if",
        "keyword": "if",
        "beforeExpr": false,
        "startsExpr": false,
        "rightAssociative": false,
        "isLoop": false,
        "isAssign": false,
        "prefix": false,
        "postfix": false,
        "binop": null,
        "updateContext": null
      },
      "value": "if",
      "start": 952,
      "end": 954,
      "loc": {
        "start": {
          "line": 26,
          "column": 2
        },
        "end": {
          "line": 26,
          "column": 4
        }
      }
    },
    {
      "type": {
        "label": "(",
        "beforeExpr": true,
        "startsExpr": true,
        "rightAssociative": false,
        "isLoop": false,
        "isAssign": false,
        "prefix": false,
        "postfix": false,
        "binop": null
      },
      "start": 955,
      "end": 956,
      "loc": {
        "start": {
          "line": 26,
          "column": 5
        },
        "end": {
          "line": 26,
          "column": 6
        }
      }
    },
    {
      "type": {
        "label": "prefix",
        "beforeExpr": true,
        "startsExpr": true,
        "rightAssociative": false,
        "isLoop": false,
        "isAssign": false,
        "prefix": true,
        "postfix": false,
        "binop": null,
        "updateContext": null
      },
      "value": "!",
      "start": 956,
      "end": 957,
      "loc": {
        "start": {
          "line": 26,
          "column": 6
        },
        "end": {
          "line": 26,
          "column": 7
        }
      }
    },
    {
      "type": {
        "label": "name",
        "beforeExpr": false,
        "startsExpr": true,
        "rightAssociative": false,
        "isLoop": false,
        "isAssign": false,
        "prefix": false,
        "postfix": false,
        "binop": null
      },
      "value": "options",
      "start": 957,
      "end": 964,
      "loc": {
        "start": {
          "line": 26,
          "column": 7
        },
        "end": {
          "line": 26,
          "column": 14
        }
      }
    },
    {
      "type": {
        "label": ")",
        "beforeExpr": false,
        "startsExpr": false,
        "rightAssociative": false,
        "isLoop": false,
        "isAssign": false,
        "prefix": false,
        "postfix": false,
        "binop": null
      },
      "start": 964,
      "end": 965,
      "loc": {
        "start": {
          "line": 26,
          "column": 14
        },
        "end": {
          "line": 26,
          "column": 15
        }
      }
    },
    {
      "type": {
        "label": "name",
        "beforeExpr": false,
        "startsExpr": true,
        "rightAssociative": false,
        "isLoop": false,
        "isAssign": false,
        "prefix": false,
        "postfix": false,
        "binop": null
      },
      "value": "options",
      "start": 966,
      "end": 973,
      "loc": {
        "start": {
          "line": 26,
          "column": 16
        },
        "end": {
          "line": 26,
          "column": 23
        }
      }
    },
    {
      "type": {
        "label": "=",
        "beforeExpr": true,
        "startsExpr": false,
        "rightAssociative": false,
        "isLoop": false,
        "isAssign": true,
        "prefix": false,
        "postfix": false,
        "binop": null,
        "updateContext": null
      },
      "value": "=",
      "start": 974,
      "end": 975,
      "loc": {
        "start": {
          "line": 26,
          "column": 24
        },
        "end": {
          "line": 26,
          "column": 25
        }
      }
    },
    {
      "type": {
        "label": "{",
        "beforeExpr": true,
        "startsExpr": true,
        "rightAssociative": false,
        "isLoop": false,
        "isAssign": false,
        "prefix": false,
        "postfix": false,
        "binop": null
      },
      "start": 976,
      "end": 977,
      "loc": {
        "start": {
          "line": 26,
          "column": 26
        },
        "end": {
          "line": 26,
          "column": 27
        }
      }
    },
    {
      "type": {
        "label": "}",
        "beforeExpr": false,
        "startsExpr": false,
        "rightAssociative": false,
        "isLoop": false,
        "isAssign": false,
        "prefix": false,
        "postfix": false,
        "binop": null
      },
      "start": 977,
      "end": 978,
      "loc": {
        "start": {
          "line": 26,
          "column": 27
        },
        "end": {
          "line": 26,
          "column": 28
        }
      }
    },
    {
      "type": {
        "label": "const",
        "keyword": "const",
        "beforeExpr": false,
        "startsExpr": false,
        "rightAssociative": false,
        "isLoop": false,
        "isAssign": false,
        "prefix": false,
        "postfix": false,
        "binop": null,
        "updateContext": null
      },
      "value": "const",
      "start": 981,
      "end": 986,
      "loc": {
        "start": {
          "line": 27,
          "column": 2
        },
        "end": {
          "line": 27,
          "column": 7
        }
      }
    },
    {
      "type": {
        "label": "name",
        "beforeExpr": false,
        "startsExpr": true,
        "rightAssociative": false,
        "isLoop": false,
        "isAssign": false,
        "prefix": false,
        "postfix": false,
        "binop": null
      },
      "value": "parameters",
      "start": 987,
      "end": 997,
      "loc": {
        "start": {
          "line": 27,
          "column": 8
        },
        "end": {
          "line": 27,
          "column": 18
        }
      }
    },
    {
      "type": {
        "label": "=",
        "beforeExpr": true,
        "startsExpr": false,
        "rightAssociative": false,
        "isLoop": false,
        "isAssign": true,
        "prefix": false,
        "postfix": false,
        "binop": null,
        "updateContext": null
      },
      "value": "=",
      "start": 998,
      "end": 999,
      "loc": {
        "start": {
          "line": 27,
          "column": 19
        },
        "end": {
          "line": 27,
          "column": 20
        }
      }
    },
    {
      "type": {
        "label": "{",
        "beforeExpr": true,
        "startsExpr": true,
        "rightAssociative": false,
        "isLoop": false,
        "isAssign": false,
        "prefix": false,
        "postfix": false,
        "binop": null
      },
      "start": 1000,
      "end": 1001,
      "loc": {
        "start": {
          "line": 27,
          "column": 21
        },
        "end": {
          "line": 27,
          "column": 22
        }
      }
    },
    {
      "type": {
        "label": "name",
        "beforeExpr": false,
        "startsExpr": true,
        "rightAssociative": false,
        "isLoop": false,
        "isAssign": false,
        "prefix": false,
        "postfix": false,
        "binop": null
      },
      "value": "header",
      "start": 1006,
      "end": 1012,
      "loc": {
        "start": {
          "line": 28,
          "column": 4
        },
        "end": {
          "line": 28,
          "column": 10
        }
      }
    },
    {
      "type": {
        "label": ":",
        "beforeExpr": true,
        "startsExpr": false,
        "rightAssociative": false,
        "isLoop": false,
        "isAssign": false,
        "prefix": false,
        "postfix": false,
        "binop": null,
        "updateContext": null
      },
      "start": 1012,
      "end": 1013,
      "loc": {
        "start": {
          "line": 28,
          "column": 10
        },
        "end": {
          "line": 28,
          "column": 11
        }
      }
    },
    {
      "type": {
        "label": "{",
        "beforeExpr": true,
        "startsExpr": true,
        "rightAssociative": false,
        "isLoop": false,
        "isAssign": false,
        "prefix": false,
        "postfix": false,
        "binop": null
      },
      "start": 1014,
      "end": 1015,
      "loc": {
        "start": {
          "line": 28,
          "column": 12
        },
        "end": {
          "line": 28,
          "column": 13
        }
      }
    },
    {
      "type": {
        "label": "string",
        "beforeExpr": false,
        "startsExpr": true,
        "rightAssociative": false,
        "isLoop": false,
        "isAssign": false,
        "prefix": false,
        "postfix": false,
        "binop": null,
        "updateContext": null
      },
      "value": "Accept-Language",
      "start": 1022,
      "end": 1039,
      "loc": {
        "start": {
          "line": 29,
          "column": 6
        },
        "end": {
          "line": 29,
          "column": 23
        }
      }
    },
    {
      "type": {
        "label": ":",
        "beforeExpr": true,
        "startsExpr": false,
        "rightAssociative": false,
        "isLoop": false,
        "isAssign": false,
        "prefix": false,
        "postfix": false,
        "binop": null,
        "updateContext": null
      },
      "start": 1039,
      "end": 1040,
      "loc": {
        "start": {
          "line": 29,
          "column": 23
        },
        "end": {
          "line": 29,
          "column": 24
        }
      }
    },
    {
      "type": {
        "label": "name",
        "beforeExpr": false,
        "startsExpr": true,
        "rightAssociative": false,
        "isLoop": false,
        "isAssign": false,
        "prefix": false,
        "postfix": false,
        "binop": null
      },
      "value": "options",
      "start": 1041,
      "end": 1048,
      "loc": {
        "start": {
          "line": 29,
          "column": 25
        },
        "end": {
          "line": 29,
          "column": 32
        }
      }
    },
    {
      "type": {
        "label": ".",
        "beforeExpr": false,
        "startsExpr": false,
        "rightAssociative": false,
        "isLoop": false,
        "isAssign": false,
        "prefix": false,
        "postfix": false,
        "binop": null,
        "updateContext": null
      },
      "start": 1048,
      "end": 1049,
      "loc": {
        "start": {
          "line": 29,
          "column": 32
        },
        "end": {
          "line": 29,
          "column": 33
        }
      }
    },
    {
      "type": {
        "label": "name",
        "beforeExpr": false,
        "startsExpr": true,
        "rightAssociative": false,
        "isLoop": false,
        "isAssign": false,
        "prefix": false,
        "postfix": false,
        "binop": null
      },
      "value": "AcceptLanguage",
      "start": 1049,
      "end": 1063,
      "loc": {
        "start": {
          "line": 29,
          "column": 33
        },
        "end": {
          "line": 29,
          "column": 47
        }
      }
    },
    {
      "type": {
        "label": ",",
        "beforeExpr": true,
        "startsExpr": false,
        "rightAssociative": false,
        "isLoop": false,
        "isAssign": false,
        "prefix": false,
        "postfix": false,
        "binop": null,
        "updateContext": null
      },
      "start": 1063,
      "end": 1064,
      "loc": {
        "start": {
          "line": 29,
          "column": 47
        },
        "end": {
          "line": 29,
          "column": 48
        }
      }
    },
    {
      "type": {
        "label": "string",
        "beforeExpr": false,
        "startsExpr": true,
        "rightAssociative": false,
        "isLoop": false,
        "isAssign": false,
        "prefix": false,
        "postfix": false,
        "binop": null,
        "updateContext": null
      },
      "value": "If-None-Match",
      "start": 1071,
      "end": 1086,
      "loc": {
        "start": {
          "line": 30,
          "column": 6
        },
        "end": {
          "line": 30,
          "column": 21
        }
      }
    },
    {
      "type": {
        "label": ":",
        "beforeExpr": true,
        "startsExpr": false,
        "rightAssociative": false,
        "isLoop": false,
        "isAssign": false,
        "prefix": false,
        "postfix": false,
        "binop": null,
        "updateContext": null
      },
      "start": 1086,
      "end": 1087,
      "loc": {
        "start": {
          "line": 30,
          "column": 21
        },
        "end": {
          "line": 30,
          "column": 22
        }
      }
    },
    {
      "type": {
        "label": "name",
        "beforeExpr": false,
        "startsExpr": true,
        "rightAssociative": false,
        "isLoop": false,
        "isAssign": false,
        "prefix": false,
        "postfix": false,
        "binop": null
      },
      "value": "options",
      "start": 1088,
      "end": 1095,
      "loc": {
        "start": {
          "line": 30,
          "column": 23
        },
        "end": {
          "line": 30,
          "column": 30
        }
      }
    },
    {
      "type": {
        "label": ".",
        "beforeExpr": false,
        "startsExpr": false,
        "rightAssociative": false,
        "isLoop": false,
        "isAssign": false,
        "prefix": false,
        "postfix": false,
        "binop": null,
        "updateContext": null
      },
      "start": 1095,
      "end": 1096,
      "loc": {
        "start": {
          "line": 30,
          "column": 30
        },
        "end": {
          "line": 30,
          "column": 31
        }
      }
    },
    {
      "type": {
        "label": "name",
        "beforeExpr": false,
        "startsExpr": true,
        "rightAssociative": false,
        "isLoop": false,
        "isAssign": false,
        "prefix": false,
        "postfix": false,
        "binop": null
      },
      "value": "IfNoneMatch",
      "start": 1096,
      "end": 1107,
      "loc": {
        "start": {
          "line": 30,
          "column": 31
        },
        "end": {
          "line": 30,
          "column": 42
        }
      }
    },
    {
      "type": {
        "label": "}",
        "beforeExpr": false,
        "startsExpr": false,
        "rightAssociative": false,
        "isLoop": false,
        "isAssign": false,
        "prefix": false,
        "postfix": false,
        "binop": null
      },
      "start": 1112,
      "end": 1113,
      "loc": {
        "start": {
          "line": 31,
          "column": 4
        },
        "end": {
          "line": 31,
          "column": 5
        }
      }
    },
    {
      "type": {
        "label": ",",
        "beforeExpr": true,
        "startsExpr": false,
        "rightAssociative": false,
        "isLoop": false,
        "isAssign": false,
        "prefix": false,
        "postfix": false,
        "binop": null,
        "updateContext": null
      },
      "start": 1113,
      "end": 1114,
      "loc": {
        "start": {
          "line": 31,
          "column": 5
        },
        "end": {
          "line": 31,
          "column": 6
        }
      }
    },
    {
      "type": {
        "label": "name",
        "beforeExpr": false,
        "startsExpr": true,
        "rightAssociative": false,
        "isLoop": false,
        "isAssign": false,
        "prefix": false,
        "postfix": false,
        "binop": null
      },
      "value": "query",
      "start": 1119,
      "end": 1124,
      "loc": {
        "start": {
          "line": 32,
          "column": 4
        },
        "end": {
          "line": 32,
          "column": 9
        }
      }
    },
    {
      "type": {
        "label": ":",
        "beforeExpr": true,
        "startsExpr": false,
        "rightAssociative": false,
        "isLoop": false,
        "isAssign": false,
        "prefix": false,
        "postfix": false,
        "binop": null,
        "updateContext": null
      },
      "start": 1124,
      "end": 1125,
      "loc": {
        "start": {
          "line": 32,
          "column": 9
        },
        "end": {
          "line": 32,
          "column": 10
        }
      }
    },
    {
      "type": {
        "label": "{",
        "beforeExpr": true,
        "startsExpr": true,
        "rightAssociative": false,
        "isLoop": false,
        "isAssign": false,
        "prefix": false,
        "postfix": false,
        "binop": null
      },
      "start": 1126,
      "end": 1127,
      "loc": {
        "start": {
          "line": 32,
          "column": 11
        },
        "end": {
          "line": 32,
          "column": 12
        }
      }
    },
    {
      "type": {
        "label": "name",
        "beforeExpr": false,
        "startsExpr": true,
        "rightAssociative": false,
        "isLoop": false,
        "isAssign": false,
        "prefix": false,
        "postfix": false,
        "binop": null
      },
      "value": "datasource",
      "start": 1134,
      "end": 1144,
      "loc": {
        "start": {
          "line": 33,
          "column": 6
        },
        "end": {
          "line": 33,
          "column": 16
        }
      }
    },
    {
      "type": {
        "label": ":",
        "beforeExpr": true,
        "startsExpr": false,
        "rightAssociative": false,
        "isLoop": false,
        "isAssign": false,
        "prefix": false,
        "postfix": false,
        "binop": null,
        "updateContext": null
      },
      "start": 1144,
      "end": 1145,
      "loc": {
        "start": {
          "line": 33,
          "column": 16
        },
        "end": {
          "line": 33,
          "column": 17
        }
      }
    },
    {
      "type": {
        "label": "name",
        "beforeExpr": false,
        "startsExpr": true,
        "rightAssociative": false,
        "isLoop": false,
        "isAssign": false,
        "prefix": false,
        "postfix": false,
        "binop": null
      },
      "value": "options",
      "start": 1146,
      "end": 1153,
      "loc": {
        "start": {
          "line": 33,
          "column": 18
        },
        "end": {
          "line": 33,
          "column": 25
        }
      }
    },
    {
      "type": {
        "label": ".",
        "beforeExpr": false,
        "startsExpr": false,
        "rightAssociative": false,
        "isLoop": false,
        "isAssign": false,
        "prefix": false,
        "postfix": false,
        "binop": null,
        "updateContext": null
      },
      "start": 1153,
      "end": 1154,
      "loc": {
        "start": {
          "line": 33,
          "column": 25
        },
        "end": {
          "line": 33,
          "column": 26
        }
      }
    },
    {
      "type": {
        "label": "name",
        "beforeExpr": false,
        "startsExpr": true,
        "rightAssociative": false,
        "isLoop": false,
        "isAssign": false,
        "prefix": false,
        "postfix": false,
        "binop": null
      },
      "value": "datasource",
      "start": 1154,
      "end": 1164,
      "loc": {
        "start": {
          "line": 33,
          "column": 26
        },
        "end": {
          "line": 33,
          "column": 36
        }
      }
    },
    {
      "type": {
        "label": ",",
        "beforeExpr": true,
        "startsExpr": false,
        "rightAssociative": false,
        "isLoop": false,
        "isAssign": false,
        "prefix": false,
        "postfix": false,
        "binop": null,
        "updateContext": null
      },
      "start": 1164,
      "end": 1165,
      "loc": {
        "start": {
          "line": 33,
          "column": 36
        },
        "end": {
          "line": 33,
          "column": 37
        }
      }
    },
    {
      "type": {
        "label": "name",
        "beforeExpr": false,
        "startsExpr": true,
        "rightAssociative": false,
        "isLoop": false,
        "isAssign": false,
        "prefix": false,
        "postfix": false,
        "binop": null
      },
      "value": "language",
      "start": 1172,
      "end": 1180,
      "loc": {
        "start": {
          "line": 34,
          "column": 6
        },
        "end": {
          "line": 34,
          "column": 14
        }
      }
    },
    {
      "type": {
        "label": ":",
        "beforeExpr": true,
        "startsExpr": false,
        "rightAssociative": false,
        "isLoop": false,
        "isAssign": false,
        "prefix": false,
        "postfix": false,
        "binop": null,
        "updateContext": null
      },
      "start": 1180,
      "end": 1181,
      "loc": {
        "start": {
          "line": 34,
          "column": 14
        },
        "end": {
          "line": 34,
          "column": 15
        }
      }
    },
    {
      "type": {
        "label": "name",
        "beforeExpr": false,
        "startsExpr": true,
        "rightAssociative": false,
        "isLoop": false,
        "isAssign": false,
        "prefix": false,
        "postfix": false,
        "binop": null
      },
      "value": "options",
      "start": 1182,
      "end": 1189,
      "loc": {
        "start": {
          "line": 34,
          "column": 16
        },
        "end": {
          "line": 34,
          "column": 23
        }
      }
    },
    {
      "type": {
        "label": ".",
        "beforeExpr": false,
        "startsExpr": false,
        "rightAssociative": false,
        "isLoop": false,
        "isAssign": false,
        "prefix": false,
        "postfix": false,
        "binop": null,
        "updateContext": null
      },
      "start": 1189,
      "end": 1190,
      "loc": {
        "start": {
          "line": 34,
          "column": 23
        },
        "end": {
          "line": 34,
          "column": 24
        }
      }
    },
    {
      "type": {
        "label": "name",
        "beforeExpr": false,
        "startsExpr": true,
        "rightAssociative": false,
        "isLoop": false,
        "isAssign": false,
        "prefix": false,
        "postfix": false,
        "binop": null
      },
      "value": "language",
      "start": 1190,
      "end": 1198,
      "loc": {
        "start": {
          "line": 34,
          "column": 24
        },
        "end": {
          "line": 34,
          "column": 32
        }
      }
    },
    {
      "type": {
        "label": "}",
        "beforeExpr": false,
        "startsExpr": false,
        "rightAssociative": false,
        "isLoop": false,
        "isAssign": false,
        "prefix": false,
        "postfix": false,
        "binop": null
      },
      "start": 1203,
      "end": 1204,
      "loc": {
        "start": {
          "line": 35,
          "column": 4
        },
        "end": {
          "line": 35,
          "column": 5
        }
      }
    },
    {
      "type": {
        "label": "}",
        "beforeExpr": false,
        "startsExpr": false,
        "rightAssociative": false,
        "isLoop": false,
        "isAssign": false,
        "prefix": false,
        "postfix": false,
        "binop": null
      },
      "start": 1207,
      "end": 1208,
      "loc": {
        "start": {
          "line": 36,
          "column": 2
        },
        "end": {
          "line": 36,
          "column": 3
        }
      }
    },
    {
      "type": {
        "label": "return",
        "keyword": "return",
        "beforeExpr": true,
        "startsExpr": false,
        "rightAssociative": false,
        "isLoop": false,
        "isAssign": false,
        "prefix": false,
        "postfix": false,
        "binop": null,
        "updateContext": null
      },
      "value": "return",
      "start": 1211,
      "end": 1217,
      "loc": {
        "start": {
          "line": 37,
          "column": 2
        },
        "end": {
          "line": 37,
          "column": 8
        }
      }
    },
    {
      "type": {
        "label": "name",
        "beforeExpr": false,
        "startsExpr": true,
        "rightAssociative": false,
        "isLoop": false,
        "isAssign": false,
        "prefix": false,
        "postfix": false,
        "binop": null
      },
      "value": "gateway",
      "start": 1218,
      "end": 1225,
      "loc": {
        "start": {
          "line": 37,
          "column": 9
        },
        "end": {
          "line": 37,
          "column": 16
        }
      }
    },
    {
      "type": {
        "label": ".",
        "beforeExpr": false,
        "startsExpr": false,
        "rightAssociative": false,
        "isLoop": false,
        "isAssign": false,
        "prefix": false,
        "postfix": false,
        "binop": null,
        "updateContext": null
      },
      "start": 1225,
      "end": 1226,
      "loc": {
        "start": {
          "line": 37,
          "column": 16
        },
        "end": {
          "line": 37,
          "column": 17
        }
      }
    },
    {
      "type": {
        "label": "name",
        "beforeExpr": false,
        "startsExpr": true,
        "rightAssociative": false,
        "isLoop": false,
        "isAssign": false,
        "prefix": false,
        "postfix": false,
        "binop": null
      },
      "value": "request",
      "start": 1226,
      "end": 1233,
      "loc": {
        "start": {
          "line": 37,
          "column": 17
        },
        "end": {
          "line": 37,
          "column": 24
        }
      }
    },
    {
      "type": {
        "label": "(",
        "beforeExpr": true,
        "startsExpr": true,
        "rightAssociative": false,
        "isLoop": false,
        "isAssign": false,
        "prefix": false,
        "postfix": false,
        "binop": null
      },
      "start": 1233,
      "end": 1234,
      "loc": {
        "start": {
          "line": 37,
          "column": 24
        },
        "end": {
          "line": 37,
          "column": 25
        }
      }
    },
    {
      "type": {
        "label": "name",
        "beforeExpr": false,
        "startsExpr": true,
        "rightAssociative": false,
        "isLoop": false,
        "isAssign": false,
        "prefix": false,
        "postfix": false,
        "binop": null
      },
      "value": "get_insurance_pricesOperation",
      "start": 1234,
      "end": 1263,
      "loc": {
        "start": {
          "line": 37,
          "column": 25
        },
        "end": {
          "line": 37,
          "column": 54
        }
      }
    },
    {
      "type": {
        "label": ",",
        "beforeExpr": true,
        "startsExpr": false,
        "rightAssociative": false,
        "isLoop": false,
        "isAssign": false,
        "prefix": false,
        "postfix": false,
        "binop": null,
        "updateContext": null
      },
      "start": 1263,
      "end": 1264,
      "loc": {
        "start": {
          "line": 37,
          "column": 54
        },
        "end": {
          "line": 37,
          "column": 55
        }
      }
    },
    {
      "type": {
        "label": "name",
        "beforeExpr": false,
        "startsExpr": true,
        "rightAssociative": false,
        "isLoop": false,
        "isAssign": false,
        "prefix": false,
        "postfix": false,
        "binop": null
      },
      "value": "parameters",
      "start": 1265,
      "end": 1275,
      "loc": {
        "start": {
          "line": 37,
          "column": 56
        },
        "end": {
          "line": 37,
          "column": 66
        }
      }
    },
    {
      "type": {
        "label": ")",
        "beforeExpr": false,
        "startsExpr": false,
        "rightAssociative": false,
        "isLoop": false,
        "isAssign": false,
        "prefix": false,
        "postfix": false,
        "binop": null
      },
      "start": 1275,
      "end": 1276,
      "loc": {
        "start": {
          "line": 37,
          "column": 66
        },
        "end": {
          "line": 37,
          "column": 67
        }
      }
    },
    {
      "type": {
        "label": "}",
        "beforeExpr": false,
        "startsExpr": false,
        "rightAssociative": false,
        "isLoop": false,
        "isAssign": false,
        "prefix": false,
        "postfix": false,
        "binop": null
      },
      "start": 1277,
      "end": 1278,
      "loc": {
        "start": {
          "line": 38,
          "column": 0
        },
        "end": {
          "line": 38,
          "column": 1
        }
      }
    },
    {
      "type": {
        "label": "const",
        "keyword": "const",
        "beforeExpr": false,
        "startsExpr": false,
        "rightAssociative": false,
        "isLoop": false,
        "isAssign": false,
        "prefix": false,
        "postfix": false,
        "binop": null,
        "updateContext": null
      },
      "value": "const",
      "start": 1280,
      "end": 1285,
      "loc": {
        "start": {
          "line": 40,
          "column": 0
        },
        "end": {
          "line": 40,
          "column": 5
        }
      }
    },
    {
      "type": {
        "label": "name",
        "beforeExpr": false,
        "startsExpr": true,
        "rightAssociative": false,
        "isLoop": false,
        "isAssign": false,
        "prefix": false,
        "postfix": false,
        "binop": null
      },
      "value": "get_insurance_pricesOperation",
      "start": 1286,
      "end": 1315,
      "loc": {
        "start": {
          "line": 40,
          "column": 6
        },
        "end": {
          "line": 40,
          "column": 35
        }
      }
    },
    {
      "type": {
        "label": "=",
        "beforeExpr": true,
        "startsExpr": false,
        "rightAssociative": false,
        "isLoop": false,
        "isAssign": true,
        "prefix": false,
        "postfix": false,
        "binop": null,
        "updateContext": null
      },
      "value": "=",
      "start": 1316,
      "end": 1317,
      "loc": {
        "start": {
          "line": 40,
          "column": 36
        },
        "end": {
          "line": 40,
          "column": 37
        }
      }
    },
    {
      "type": {
        "label": "{",
        "beforeExpr": true,
        "startsExpr": true,
        "rightAssociative": false,
        "isLoop": false,
        "isAssign": false,
        "prefix": false,
        "postfix": false,
        "binop": null
      },
      "start": 1318,
      "end": 1319,
      "loc": {
        "start": {
          "line": 40,
          "column": 38
        },
        "end": {
          "line": 40,
          "column": 39
        }
      }
    },
    {
      "type": {
        "label": "name",
        "beforeExpr": false,
        "startsExpr": true,
        "rightAssociative": false,
        "isLoop": false,
        "isAssign": false,
        "prefix": false,
        "postfix": false,
        "binop": null
      },
      "value": "path",
      "start": 1322,
      "end": 1326,
      "loc": {
        "start": {
          "line": 41,
          "column": 2
        },
        "end": {
          "line": 41,
          "column": 6
        }
      }
    },
    {
      "type": {
        "label": ":",
        "beforeExpr": true,
        "startsExpr": false,
        "rightAssociative": false,
        "isLoop": false,
        "isAssign": false,
        "prefix": false,
        "postfix": false,
        "binop": null,
        "updateContext": null
      },
      "start": 1326,
      "end": 1327,
      "loc": {
        "start": {
          "line": 41,
          "column": 6
        },
        "end": {
          "line": 41,
          "column": 7
        }
      }
    },
    {
      "type": {
        "label": "string",
        "beforeExpr": false,
        "startsExpr": true,
        "rightAssociative": false,
        "isLoop": false,
        "isAssign": false,
        "prefix": false,
        "postfix": false,
        "binop": null,
        "updateContext": null
      },
      "value": "/insurance/prices/",
      "start": 1328,
      "end": 1348,
      "loc": {
        "start": {
          "line": 41,
          "column": 8
        },
        "end": {
          "line": 41,
          "column": 28
        }
      }
    },
    {
      "type": {
        "label": ",",
        "beforeExpr": true,
        "startsExpr": false,
        "rightAssociative": false,
        "isLoop": false,
        "isAssign": false,
        "prefix": false,
        "postfix": false,
        "binop": null,
        "updateContext": null
      },
      "start": 1348,
      "end": 1349,
      "loc": {
        "start": {
          "line": 41,
          "column": 28
        },
        "end": {
          "line": 41,
          "column": 29
        }
      }
    },
    {
      "type": {
        "label": "name",
        "beforeExpr": false,
        "startsExpr": true,
        "rightAssociative": false,
        "isLoop": false,
        "isAssign": false,
        "prefix": false,
        "postfix": false,
        "binop": null
      },
      "value": "method",
      "start": 1352,
      "end": 1358,
      "loc": {
        "start": {
          "line": 42,
          "column": 2
        },
        "end": {
          "line": 42,
          "column": 8
        }
      }
    },
    {
      "type": {
        "label": ":",
        "beforeExpr": true,
        "startsExpr": false,
        "rightAssociative": false,
        "isLoop": false,
        "isAssign": false,
        "prefix": false,
        "postfix": false,
        "binop": null,
        "updateContext": null
      },
      "start": 1358,
      "end": 1359,
      "loc": {
        "start": {
          "line": 42,
          "column": 8
        },
        "end": {
          "line": 42,
          "column": 9
        }
      }
    },
    {
      "type": {
        "label": "string",
        "beforeExpr": false,
        "startsExpr": true,
        "rightAssociative": false,
        "isLoop": false,
        "isAssign": false,
        "prefix": false,
        "postfix": false,
        "binop": null,
        "updateContext": null
      },
      "value": "get",
      "start": 1360,
      "end": 1365,
      "loc": {
        "start": {
          "line": 42,
          "column": 10
        },
        "end": {
          "line": 42,
          "column": 15
        }
      }
    },
    {
      "type": {
        "label": "}",
        "beforeExpr": false,
        "startsExpr": false,
        "rightAssociative": false,
        "isLoop": false,
        "isAssign": false,
        "prefix": false,
        "postfix": false,
        "binop": null
      },
      "start": 1366,
      "end": 1367,
      "loc": {
        "start": {
          "line": 43,
          "column": 0
        },
        "end": {
          "line": 43,
          "column": 1
        }
      }
    },
    {
      "type": {
        "label": "eof",
        "beforeExpr": false,
        "startsExpr": false,
        "rightAssociative": false,
        "isLoop": false,
        "isAssign": false,
        "prefix": false,
        "postfix": false,
        "binop": null,
        "updateContext": null
      },
      "start": 1368,
      "end": 1368,
      "loc": {
        "start": {
          "line": 44,
          "column": 0
        },
        "end": {
          "line": 44,
          "column": 0
        }
      }
    }
  ]
}